typed_astunparse/__init__.py
typed_astunparse/_version.py
typed_astunparse/printer.py
typed_astunparse/py.typed
typed_astunparse/unparser.py
typed_astunparse-2.1.4.dist-info/LICENSE
typed_astunparse-2.1.4.dist-info/METADATA
typed_astunparse-2.1.4.dist-info/NOTICE
typed_astunparse-2.1.4.dist-info/WHEEL
typed_astunparse-2.1.4.dist-info/top_level.txt
typed_astunparse-2.1.4.dist-info/RECORD
